tiny_proxy/__init__.py
tiny_proxy/_errors.py
tiny_proxy/_stream.py
tiny_proxy/_tunnel.py
tiny_proxy/_handlers/__init__.py
tiny_proxy/_handlers/base.py
tiny_proxy/_handlers/http.py
tiny_proxy/_handlers/socks4.py
tiny_proxy/_handlers/socks5.py
tiny_proxy/_proxy/__init__.py
tiny_proxy/_proxy/abc.py
tiny_proxy/_proxy/http.py
tiny_proxy/_proxy/socks4.py
tiny_proxy/_proxy/socks5.py
tiny_proxy-0.2.1.dist-info/LICENSE.txt
tiny_proxy-0.2.1.dist-info/METADATA
tiny_proxy-0.2.1.dist-info/WHEEL
tiny_proxy-0.2.1.dist-info/top_level.txt
tiny_proxy-0.2.1.dist-info/RECORD
