Metadata-Version: 2.1
Name: tiny-proxy
Version: 0.2.1
Summary: Simple proxy server (SOCKS4(a), SOCKS5(h), HTTP tunnel)
Home-page: https://github.com/romis2012/tiny-proxy
Author: Roman Snegirev
Author-email: snegiryev@gmail.com
License: Apache 2
Keywords: socks socks5 socks4 http proxy server asyncio trio anyio
Platform: UNKNOWN
License-File: LICENSE.txt
Requires-Dist: anyio (<5.0,>=3.6.1)
